mcutils/__init__.py
mcutils/cli.py
mcutils/input_validation.py
mcutils/json_manager.py
mcutils/logger.py
mcutils/mcutils.py
mcutils/print_manager.py
mcutils-0.0.8.dist-info/METADATA
mcutils-0.0.8.dist-info/WHEEL
mcutils-0.0.8.dist-info/entry_points.txt
mcutils-0.0.8.dist-info/top_level.txt
mcutils-0.0.8.dist-info/RECORD
