Metadata-Version: 2.1
Name: mcutils
Version: 0.0.8
Summary: Python Boilerplate contains all the boilerplate you need to create a Python package.
Home-page: https://github.com/macanepa/mcutils
Author: Matias Canepa Gonzalez
Author-email: macanepa@miuandes.cl
License: GNU General Public License v3
Keywords: mcutils
Platform: UNKNOWN
Classifier: Development Status :: 2 - Pre-Alpha
Classifier: Intended Audience :: Developers
Classifier: License :: OSI Approved :: GNU General Public License v3 (GPLv3)
Classifier: Natural Language :: English
Classifier: Programming Language :: Python :: 3
Classifier: Programming Language :: Python :: 3.5
Classifier: Programming Language :: Python :: 3.6
Classifier: Programming Language :: Python :: 3.7
Classifier: Programming Language :: Python :: 3.8
Requires-Python: >=3.5
Requires-Dist: Click (>=7.0)
